Products.CMFUid-4.2-py3.11-nspkg.pth
Products/CMFUid/UniqueIdAnnotationTool.py
Products/CMFUid/UniqueIdGeneratorTool.py
Products/CMFUid/UniqueIdHandlerTool.py
Products/CMFUid/__init__.py
Products/CMFUid/configure.zcml
Products/CMFUid/event.zcml
Products/CMFUid/interfaces.py
Products/CMFUid/testing.py
Products/CMFUid/tool.gif
Products/CMFUid/profiles/default/catalog.xml
Products/CMFUid/profiles/default/componentregistry.xml
Products/CMFUid/profiles/default/toolset.xml
Products/CMFUid/tests/__init__.py
Products/CMFUid/tests/test_uidannotation.py
Products/CMFUid/tests/test_uidgeneration.py
Products/CMFUid/tests/test_uidhandling.py
Products/CMFUid/www/queryUID.pt
Products.CMFUid-4.2.dist-info/LICENSE.txt
Products.CMFUid-4.2.dist-info/METADATA
Products.CMFUid-4.2.dist-info/WHEEL
Products.CMFUid-4.2.dist-info/entry_points.txt
Products.CMFUid-4.2.dist-info/namespace_packages.txt
Products.CMFUid-4.2.dist-info/top_level.txt
Products.CMFUid-4.2.dist-info/RECORD
