Metadata-Version: 2.1
Name: Products.CMFUid
Version: 4.2
Summary: Uid product for the Zope Content Management Framework
Home-page: https://github.com/zopefoundation/Products.CMFUid
Author: Zope Foundation and Contributors
Author-email: zope-dev@zope.dev
License: ZPL 2.1
Keywords: web application server zope cmf
Classifier: Development Status :: 5 - Production/Stable
Classifier: Framework :: Plone
Classifier: Framework :: Zope :: 5
Classifier: Intended Audience :: Developers
Classifier: License :: OSI Approved :: Zope Public License
Classifier: Programming Language :: Python :: 3
Classifier: Programming Language :: Python :: 3.7
Classifier: Programming Language :: Python :: 3.8
Classifier: Programming Language :: Python :: 3.9
Classifier: Programming Language :: Python :: 3.10
Classifier: Programming Language :: Python :: 3.11
Classifier: Topic :: Software Development
Classifier: Topic :: Software Development :: Libraries :: Application Frameworks
Requires-Python: >=3.7
License-File: LICENSE.txt
Requires-Dist: Products.CMFCore >=2.4.0dev
Requires-Dist: Products.ZCatalog >=4.1.1
Requires-Dist: Zope
Requires-Dist: setuptools
Provides-Extra: test
Requires-Dist: zope.testing >=3.7.0 ; extra == 'test'
